[
  {
    "id": "leeds-vs-west-ham",
    "team1": {
      "name": "Leeds",
      "logo": "https://cdn.sportfeeds.io/sdl/images/team/crest/medium/aHnEa_wImk48agGWeQmpX.png"
    },
    "team2": {
      "name": "West Ham",
      "logo": "https://cdn.sportfeeds.io/sdl/images/team/crest/medium/CCygH4qVdQFkGTvjHdtDp.png"
    },
    "matchTime": "2025-10-24T19:00:00.000Z",
    "endTime": ""
  },
  {
    "id": "real-sociedad-vs-sevilla",
    "team1": {
      "name": "Real Sociedad",
      "logo": "https://cdn.sportfeeds.io/sdl/images/team/crest/medium/N79j9O-sTkXZNhc9UZUsX.png"
    },
    "team2": {
      "name": "Sevilla",
      "logo": "https://cdn.sportfeeds.io/sdl/images/team/crest/medium/crn6HYOO9QzfqMRAUuGIF.png"
    },
    "matchTime": "2025-10-24T19:00:00.000Z",
    "endTime": ""
  },
  {
    "id": "ac-milan-vs-pisa",
    "team1": {
      "name": "AC Milan",
      "logo": "https://cdn.sportfeeds.io/sdl/images/team/crest/medium/KxcpyOfGuTCkPqCgyf-Rr.png"
    },
    "team2": {
      "name": "Pisa",
      "logo": "https://cdn.sportfeeds.io/sdl/images/team/crest/medium/LpjGeUbRU3JnZRCCIqJRU.png"
    },
    "matchTime": "2025-10-24T18:45:00.000Z",
    "endTime": ""
  }
]