{
  "vfb-stuttgart-vs-fc-heidenheim": [
    {
      "name": "FANCODE",
      "player": "f1",
      "stream_link": "https://api.game24x.xyz/gg.html?id=fc1"
    }
  ],
  "uruguay-vs-uzbekistan": [
    {
      "name": "Server 1",
      "player": "f1",
      "stream_link": "https://dash-hex.pages.dev/p?p=https://saz.blitzen.store/wwe.m3u8"
    }
  ],
  "canada-vs-colombia": [
    {
      "name": "Server 1",
      "player": "f1",
      "stream_link": "https://dash-hex.pages.dev/ADB?c=https://jumpshare.com/embed/e4dsEEIxdkmWkSbT34dn"
    }
  ],
  "tottenham-vs-aston-villa": [
    {
      "name": "Server 1",
      "player": "f1",
      "stream_link": "https://dash-hex.pages.dev/ADB?c=https://jumpshare.com/embed/e4dsEEIxdkmWkSbT34dn"
    }
  ],
  "liverpool-vs-manchester-united": [
    {
      "name": "Server 1",
      "player": "f1",
      "stream_link": "https://dash-hex.pages.dev/ADB?c=https://jumpshare.com/embed/e4dsEEIxdkmWkSbT34dn"
    }
  ],
  "elche-vs-athletic-bilbao": [
    {
      "name": "Server 1",
      "player": "f1",
      "stream_link": "https://dash-hex.pages.dev/ADB?c=https://jumpshare.com/embed/e4dsEEIxdkmWkSbT34dn"
    }
  ],
  "celta-vigo-vs-real-sociedad": [
    {
      "name": "Server 1",
      "player": "f1",
      "stream_link": "https://dash-hex.pages.dev/ADB?c=https://jumpshare.com/embed/e4dsEEIxdkmWkSbT34dn"
    }
  ],
  "getafe-vs-real-madrid": [
    {
      "name": "Server 1",
      "player": "f1",
      "stream_link": "https://dash-hex.pages.dev/ADB?c=https://jumpshare.com/embed/e4dsEEIxdkmWkSbT34dn"
    }
  ],
  "ac-milan-vs-fiorentina": [
    {
      "name": "Server 1",
      "player": "f1",
      "stream_link": "https://dash-hex.pages.dev/ADB?c=https://jumpshare.com/embed/e4dsEEIxdkmWkSbT34dn"
    }
  ],
  "argentina-u20-vs-morocco-u20": [
    {
      "name": "Server 1",
      "player": "f1",
      "stream_link": "https://dash-hex.pages.dev/ADB?c=https://jumpshare.com/embed/e4dsEEIxdkmWkSbT34dn"
    }
  ],
  "australia-vs-india": [
    {
      "name": "TNT SPORTS 1",
      "player": "pl1",
      "stream_link": "tnt1"
    },
    {
      "name": "FOX IOS",
      "player": "f1",
      "stream_link": "https://hex-seven.vercel.app/drmplay.html?mpd=https%3A%2F%2Ffoxhindi.pages.dev%2Fplaylist.m3u8&keyid=null&key=null"
    },
    {
      "name": "NS Player",
      "player": "ns",
      "stream_link": "https://ottb.live.cf.ww.aiv-cdn.net/lhr-nitro/live/dash/enc/wf8usag51e/out/v1/bd3b0c314fff4bb1ab4693358f3cd2d3/cenc.mpd?|drmScheme=clearkey&drmLicense=d0f2e5c39e70c18f29bf77768a1ad89a:d6853c51fcf37a18905f0609972395d7"
    }
  ]
}